midas/__init__.py
midas/api/__init__.py
midas/api/fnc_analyze.py
midas/api/fnc_configure.py
midas/api/fnc_download.py
midas/api/fnc_list.py
midas/api/fnc_run.py
midas/api/midasctl.py
midas/scenario/__init__.py
midas/scenario/configurator.py
midas/scenario/scenario.py
midas/scenario/upgrade_module.py
midas/scenario/default_scenarios/bremerhaven.yml
midas/scenario/default_scenarios/four_bus.yml
midas/scenario/default_scenarios/midaslv.yml
midas/scenario/default_scenarios/midasmv.yml
midas/tools/__init__.py
midas/tools/palaestrai/__init__.py
midas/tools/palaestrai/database_view.py
midas/tools/palaestrai/reactive_power_muscle.py
midas/tools/palaestrai/rewards.py
midas/util/__init__.py
midas/util/compute_q.py
midas/util/config_util.py
midas/util/dateformat.py
midas/util/dict_util.py
midas/util/logging.py
midas/util/print_format.py
midas/util/report_util.py
midas/util/runtime_config.py
midas_mosaik-2.0.2.dist-info/METADATA
midas_mosaik-2.0.2.dist-info/WHEEL
midas_mosaik-2.0.2.dist-info/entry_points.txt
midas_mosaik-2.0.2.dist-info/licenses/LICENSE
midas_mosaik-2.0.2.dist-info/RECORD
