Metadata-Version: 2.4
Name: midas-mosaik
Version: 2.0.2
Summary: MultI-DomAin test Scenario for smart grid co-simulation.
Project-URL: Documentation, https://midas-mosaik.gitlab.io/midas
Author-email: Stephan Balduin <stephan.balduin@offis.de>
License-File: LICENSE
Requires-Python: >=3.8
Requires-Dist: appdirs
Requires-Dist: click
Requires-Dist: mosaik>=3.4.0
Requires-Dist: pandas
Requires-Dist: ruamel-yaml
Provides-Extra: arl
Requires-Dist: midas-comdata~=2.0.0; extra == 'arl'
Requires-Dist: midas-dlpdata~=2.0.0; extra == 'arl'
Requires-Dist: midas-palaestrai>=3.5.4; extra == 'arl'
Requires-Dist: midas-powergrid~=2.0.0; extra == 'arl'
Requires-Dist: midas-pwdata~=2.0.0; extra == 'arl'
Requires-Dist: midas-sndata~=2.0.0; extra == 'arl'
Requires-Dist: midas-store>=2.0.0; extra == 'arl'
Requires-Dist: midas-timesim~=2.0.0; extra == 'arl'
Requires-Dist: midas-weather~=2.0.0; extra == 'arl'
Requires-Dist: palaestrai-mosaik>=3.5.4; extra == 'arl'
Requires-Dist: pysimmods~=0.20.0; extra == 'arl'
Provides-Extra: base
Requires-Dist: midas-comdata~=2.0.0; extra == 'base'
Requires-Dist: midas-powergrid~=2.0.0; extra == 'base'
Requires-Dist: midas-sndata~=2.0.0; extra == 'base'
Requires-Dist: midas-store>=2.0.0; extra == 'base'
Requires-Dist: midas-weather~=2.0.0; extra == 'base'
Requires-Dist: pysimmods~=0.20.0; extra == 'base'
Provides-Extra: bh
Requires-Dist: midas-dlpdata~=2.0.0; extra == 'bh'
Requires-Dist: midas-powergrid~=2.0.0; extra == 'bh'
Requires-Dist: midas-pwdata~=2.0.0; extra == 'bh'
Requires-Dist: midas-store>=2.0.0; extra == 'bh'
Provides-Extra: dev
Requires-Dist: build; extra == 'dev'
Requires-Dist: coverage; extra == 'dev'
Requires-Dist: pytest; extra == 'dev'
Requires-Dist: ruff; extra == 'dev'
Requires-Dist: twine; extra == 'dev'
Provides-Extra: full
Requires-Dist: midas-comdata~=2.0.0; extra == 'full'
Requires-Dist: midas-dlpdata~=2.0.0; extra == 'full'
Requires-Dist: midas-powergrid~=2.0.0; extra == 'full'
Requires-Dist: midas-pwdata~=2.0.0; extra == 'full'
Requires-Dist: midas-sndata~=2.0.0; extra == 'full'
Requires-Dist: midas-store>=2.0.0; extra == 'full'
Requires-Dist: midas-timesim~=2.0.0; extra == 'full'
Requires-Dist: midas-weather~=2.0.0; extra == 'full'
Requires-Dist: pysimmods~=0.20.0; extra == 'full'
